whisper/__init__.py
whisper/__main__.py
whisper/audio.py
whisper/decoding.py
whisper/model.py
whisper/timing.py
whisper/tokenizer.py
whisper/transcribe.py
whisper/triton_ops.py
whisper/utils.py
whisper/version.py
whisper/assets/gpt2.tiktoken
whisper/assets/mel_filters.npz
whisper/assets/multilingual.tiktoken
whisper/normalizers/__init__.py
whisper/normalizers/basic.py
whisper/normalizers/english.json
whisper/normalizers/english.py
whisper_applemps-20240930.dist-info/LICENSE
whisper_applemps-20240930.dist-info/METADATA
whisper_applemps-20240930.dist-info/WHEEL
whisper_applemps-20240930.dist-info/entry_points.txt
whisper_applemps-20240930.dist-info/top_level.txt
whisper_applemps-20240930.dist-info/RECORD
