Metadata-Version: 2.1
Name: whisper-applemps
Version: 20240930
Summary: Robust Speech Recognition via Large-Scale Weak Supervision
Home-page: https://github.com/openai/whisper
Author: Doctor-yoi
License: MIT
Requires-Python: >=3.11
License-File: LICENSE
Requires-Dist: numba
Requires-Dist: numpy
Requires-Dist: torch
Requires-Dist: tqdm
Requires-Dist: more-itertools
Requires-Dist: tiktoken
Requires-Dist: requests
Requires-Dist: urllib3 ==1.24.2
Requires-Dist: triton >=2.0.0 ; platform_machine == "x86_64" and sys_platform == "linux" or sys_platform == "linux2"
Provides-Extra: dev
Requires-Dist: pytest ; extra == 'dev'
Requires-Dist: scipy ; extra == 'dev'
Requires-Dist: black ; extra == 'dev'
Requires-Dist: flake8 ; extra == 'dev'
Requires-Dist: isort ; extra == 'dev'
